{
  "jointimes": [
    {
      "image": "http://gardenpaper.in/wp-content/uploads/2019/07/sanpadabuilding.jpg",
      "title": "рдореБрдВрдмрдИ рдЕрд╢реНрд╡рдореЗрдз рд╢рдкрде рд╕рдВрдХрд▓реНрдк ",
      "date": "28 Aug 2019",
      "s": "34",
      "author": "рдЕрд╢реНрд╡рдореЗрдз рдорд╣рд╛рдпрдЬреНрдЮ рд╕рдорд┐рддрд┐, рдореБрдВрдмрдИ",
      "content": "*рдореБрдВрдмрдИ рдЕрд╢реНрд╡рдореЗрдз рд╢рдкрде рд╕рдВрдХрд▓реНрдк *\n\n\n\nрдЖрддреНрдореАрдп рдкрд░рд┐рдЬрди,\n\n\n\nрдореБрдВрдмрдИ рдореЗрдВ 6 рд╕реЗ 11 рдЬрдирд╡рд░реА 2021 рдХреЗ рдордзреНрдп рд╕рдВрдкрдиреНрди рд╣реЛрдиреЗ рд╡рд╛рд▓реЗ рдЗрд╕ рдРрддрд┐рд╣рд╛рд╕рд┐рдХ рдпрдЬреНрдЮ рдХреА рд╕рдлрд▓рддрд╛ рдЕрдЧрд░ рдХрд┐рд╕реА рдмрд╛рдд рдкрд░ рдирд┐рд░реНрднрд░ рдХрд░рддреА рд╣реИ рддреЛ рд╡рд╣ рд╣реИ, рдЖрдкрдХреА рдкреНрд░рддрд┐рдмрджреНрдзрддрд╛ рдФрд░ рд╕рдорд░реНрдкрдг ред \n\n\n\nрдЕрд╢реНрд╡рдореЗрдз рдЬреИрд╕реА рджреИрд╡реАрдп рдпреЛрдЬрдирд╛ рдХреЛ рдкреВрд░реНрдг рдХрд░рдиреЗ рд╣реЗрддреБ рдХрд░реНрдорда, рдкреНрд░рд╛рдгрд╡рд╛рди рдХрд░реНрдордпреЛрдЧрд┐рдпреЛрдВ рдХреА рдЖрд╡рд╢реНрдпрдХрддрд╛ рд╣реЛрддреА рд╣реИ рдЬреЛ рдЕрдкрдиреЗ рддрдк-рдмрд▓ рджреНрд╡рд╛рд░рд╛  рдмреНрд░рд╣реНрдорд╛рдВрдб рдореЗрдВ рдПрдХ рдРрд╕реА рдКрд░реНрдЬрд╛ рдкреИрджрд╛ рдХрд░ рд╕рдХреЗрдВ рдЬреЛ рдЗрд╕ рдРрддрд┐рд╣рд╛рд╕рд┐рдХ рдЖрдпреЛрдЬрди рдХреЛ рд╕рдлрд▓рддрд╛ рдХреЗ рд╢рд┐рдЦрд░ рддрдХ рдкрд╣реБрдБрдЪрд╛ рд╕рдХреЗред\n\n\n\nрдХрд┐рд╕реА рднреА рдЕрдиреБрд╖реНрдард╛рди рдХреЛ рд╕реБрд╕рдВрдкрдиреНрди рдХрд░рдиреЗ рд╣реЗрддреБ рддрди- рдорди -рдзрди рдХреА рдЖрд╡рд╢реНрдпрдХрддрд╛ рд╣реЛрддреА рд╣реИред  рдЖрдк рд╕рдмрд╕реЗ рдирд┐рд╡реЗрджрди рд╣реИ рдХрд┐ рдЬрд┐рд╕рд╕реЗ рдЬреЛ рдмрди рдкрдбрд╝реЗ рд╡реИрд╕рд╛ рд╕рд╣рдпреЛрдЧ рдХрд░рдиреЗ рдХрд╛ рдкреНрд░рдпрд╛рд╕ рдХрд░реЗрдВред\n\n\n\nрдкрд░рд┐рдЬрди рдЕрдкрдиреА рд╕реБрд╡рд┐рдзрд╛рдиреБрд╕рд╛рд░ рдЗрдирдореЗрдВ рд╕реЗ рдХреЛрдИ рднреА рдПрдХ рд╡рд┐рдХрд▓реНрдк рдЪреБрди рдХрд░ рдЗрд╕ рджрд┐рд╡реНрдп рдЖрдпреЛрдЬрди рд╣реЗрддреБ рдЕрдкрдиреА  рднрд╛рдЧреАрджрд╛рд░реА рдХрд░ рд╕рдХрддреЗ рд╣реИрдВ - \n\n\n\n1. 24000 рдЧрд╛рдпрддреНрд░реА рдордВрддреНрд░ рдХрд╛ рдПрдХ рд▓рдШреБ рдЕрдиреБрд╖реНрдард╛рди рд╕рдВрдкрдиреНрди рдХрд░рдХреЗ (рддрдк рджрд╛рди) + рдЕрд╢реНрд╡рдореЗрдз рд╣реЗрддреБ рдЕрдкрдиреА рдПрдХ рдорд╛рд╣ рдХрд╛ рд╡реЗрддрди рдХреЗ рд░реВрдк рдореЗрдВ ред(рдЕрдВрд╢рджрд╛рди)\n\n\n\n2. рдЕрд╢реНрд╡рдореЗрдз рдХреА рд╕рдлрд▓рддрд╛ рд╣реЗрддреБ рдПрдХ рдорд╛рд╣ рдХрд╛ рд╕рдордпрджрд╛рдиред (рд╢реНрд░рдорджрд╛рди) + рдЕрд╢реНрд╡рдореЗрдз рд╣реЗрддреБ рдЕрдкрдиреА рдПрдХ рдорд╛рд╣ рдХрд╛ рд╡реЗрддрди рдХреЗ рд░реВрдк рдореЗрдВ ред(рдЕрдВрд╢рджрд╛рди)\n\n\n\n3. 24000 рдЧрд╛рдпрддреНрд░реА рдордВрддреНрд░ рдХрд╛ рдПрдХ рд▓рдШреБ рдЕрдиреБрд╖реНрдард╛рди рд╕рдВрдкрдиреНрди рдХрд░рдХреЗ (рддрдк рджрд╛рди) + рдЕрд╢реНрд╡рдореЗрдз рд╣реЗрддреБ рдЕрдкрдиреА рдПрдХ рдорд╛рд╣ рдХрд╛ рд╡реЗрддрди рдХреЗ рд░реВрдк рдореЗрдВ ред(рдЕрдВрд╢рджрд╛рди) + рдЕрд╢реНрд╡рдореЗрдз рдХреА рд╕рдлрд▓рддрд╛ рд╣реЗрддреБ рдПрдХ рдорд╛рд╣ рдХрд╛ рд╕рдордпрджрд╛рдиред (рд╢реНрд░рдорджрд╛рди)\n\n\n\n4. реи рд╢рдкрде рд╕рдВрдХрд▓реНрдк рдкреБрд╕реНрддрд┐рдХрд╛ рднрд░рдиреЗ рдХрд╛ рдЙрддреНрддрд░рджрд╛рдпрд┐рддреНрд╡ + реирекрежрежреж рдЧрд╛рдпрддреНрд░реА рдордВрддреНрд░ рд▓рдШреБ рдЕрдиреБрд╖реНрдард╛рди\n\n\n\n\nрдЕрд╢реНрд╡рдореЗрдз рдорд╣рд╛рдпрдЬреНрдЮ рд╕реБрд╕рдВрдкрдиреНрди рдХрд░рдиреЗ рд╣реЗрддреБ рднрд╛рдЧреАрд░рдереА рдкреНрд░рдпрд╛рд╕ рдХреА рдЖрд╡рд╢реНрдпрдХрддрд╛ рд╣реИ рдФрд░ рд╕рдмрд╕реЗ рдЕрдиреБрд░реЛрдз рд╣реИ рдХрд┐ рдЕрдкрдиреЗ рдЕрдВрджрд░ рдЫрд┐рдкреЗ рдмреИрдареЗ рднрдЧреАрд░рде рдХрд╛ рдЖрд╣реНрд╡рд╛рди рдХрд░реЗрдВ рдФрд░ рдЕрдкрдиреЗ рдкреБрд░реБрд╖рд╛рд░реНрде рдХреЛ рдЗрд╕ рдорд╣рд╛рдиреБрд╖реНрдард╛рди рд╣реЗрддреБ  рд╕рдорд░реНрдкрд┐рдд рдХрд░реЗрдВ ред рдЖрдЗрдП, рдорд╣рд╛рдХрд╛рд▓ рдХреА рдЗрд╕ рджреИрд╡реАрдп рдпреЛрдЬрдирд╛ рдореЗрдВ рдЕрдкрдиреА рд╕рдХреНрд░рд┐рдп рднреВрдорд┐рдХрд╛ рдирд┐рднрд╛рддреЗ рд╣реБрдП рдЕрдкрдиреА рднрд╛рдЧреАрджрд╛рд░реА рд╕реБрдирд┐рд╢реНрдЪрд┐рдд рдХрд░реЗрдВред\n\n\nрдкрдВрдЬреАрдХрд░рдг рдХрд░реЗрдВ - Registration link - https://forms.gle/ePS4hFKPUnjLjG9J6 \n\n\n\nрд╕рдВрдкрд░реНрдХ рд╕реВрддреНрд░ - \n\n\n\nemail .              mumbai.ashwamedha@gmail.com\n\n\nfacebook         http://www.facebook.com/Mumbai.Ashwamedha.2021\n\n\nTwitter             @MAshwamedha\n\n\nInstagram       mumbai.ashwamedha\n\n\n\n\n\nЁЯОаЁЯФеЁЯОаЁЯФеЁЯОаЁЯФеЁЯОаЁЯОаЁЯФеЁЯОаЁЯФеЁЯОаЁЯФеЁЯОаЁЯОаЁЯФеЁЯОаЁЯФеЁЯОаЁЯФеЁЯОаЁЯОаЁЯФеЁЯОаЁЯФеЁЯОаЁЯФеЁЯОаЁЯОаЁЯФеЁЯОаЁЯФеЁЯОаЁЯФеЁЯОаЁЯОаЁЯФеЁЯОаЁЯФеЁЯОа\n\n\n\n\n\nDear All, \n\n\n\nThe countdown to Ashwamedh Yagya '21 has begun. ( 6th to 11th Jan 2021 )\n\n\n\nhis historic Yagya, the like of which has never ever taken place in Mumbai will be a success, only because of your dedication and devotion. \n\n\n\nCome let us be a dynamic part of this mega, time churning divine event by registering our bit. \n\n\n\nThe Ashwamedh seeks dynamic Karmyogis who can whip up the energy from the Universe with their Tapobal in the following ways -\n\n\n\nPlease choose any one option.\n\n\n\n1. Perform a mini-anushthan of 24000 Gayatri Mantras + Donate a month's salary towards Ashwamedh\n\n\n\n2. Donate one month's time towards the success of Ashwamedh Yagya + Donate a month's salary towards Ashwamedh\n\n\n\n3. Perform a mini-anushthan of 24000 Gayatri Mantras + Donate a month's salary towards Ashwamedh + Donate one month's time towards the success of Ashwamedh Yagya\n\n\n\n4. Fill two Sankalp Book + 24000 Gayatri Laghu Anusthan\n\n\n\nAll the parijans! Bring out the Bhagirath from within you, and surrender yourself to this noblest of all endeavors - this Mahayagya of Ashwamedh! \n\n\n\n\nContact us at - \n\n\n\nemail .              mumbai.ashwamedha@gmail.com\n\nfacebook         http://www.facebook.com/Mumbai.Ashwamedha.2021\n\nTwitter             @MAshwamedha\n\nInstagram       mumbai.ashwamedha\n\n\n\nRegistration link - https://forms.gle/ePS4hFKPUnjLjG9J6 \n\nForward  to your dear one\n\n\n\nЁЯЩП"
    }
  ]
}
